crownstone_uart/Constants.py
crownstone_uart/Exceptions.py
crownstone_uart/__init__.py
crownstone_uart/core/CrownstoneUart.py
crownstone_uart/core/UartEventBus.py
crownstone_uart/core/__init__.py
crownstone_uart/core/containerClasses/MeshResult.py
crownstone_uart/core/containerClasses/__init__.py
crownstone_uart/core/dataFlowManagers/BatchCollector.py
crownstone_uart/core/dataFlowManagers/Collector.py
crownstone_uart/core/dataFlowManagers/StoneManager.py
crownstone_uart/core/dataFlowManagers/StoneStateManager.py
crownstone_uart/core/dataFlowManagers/UartWriter.py
crownstone_uart/core/dataFlowManagers/__init__.py
crownstone_uart/core/modules/AssetFilterHandler.py
crownstone_uart/core/modules/ControlHandler.py
crownstone_uart/core/modules/MeshHandler.py
crownstone_uart/core/modules/MicroappHandler.py
crownstone_uart/core/modules/SetupHandler.py
crownstone_uart/core/modules/StateHandler.py
crownstone_uart/core/modules/UsbDevHandler.py
crownstone_uart/core/modules/__init__.py
crownstone_uart/core/uart/UartBridge.py
crownstone_uart/core/uart/UartManager.py
crownstone_uart/core/uart/UartParser.py
crownstone_uart/core/uart/UartReadBuffer.py
crownstone_uart/core/uart/UartTypes.py
crownstone_uart/core/uart/__init__.py
crownstone_uart/core/uart/uartPackets/AdcChannelPacket.py
crownstone_uart/core/uart/uartPackets/AdcConfigPacket.py
crownstone_uart/core/uart/uartPackets/AssetIdReport.py
crownstone_uart/core/uart/uartPackets/AssetMacReport.py
crownstone_uart/core/uart/uartPackets/CurrentSamplesPacket.py
crownstone_uart/core/uart/uartPackets/PowerCalculationPacket.py
crownstone_uart/core/uart/uartPackets/RssiBetweenStonesPacket.py
crownstone_uart/core/uart/uartPackets/UartCommandHelloPacket.py
crownstone_uart/core/uart/uartPackets/UartCrownstoneHelloPacket.py
crownstone_uart/core/uart/uartPackets/UartCrownstoneStatusPacket.py
crownstone_uart/core/uart/uartPackets/UartLogArrayPacket.py
crownstone_uart/core/uart/uartPackets/UartLogHeaderPacket.py
crownstone_uart-2.7.0.dist-info/LICENSE-APACHE
crownstone_uart-2.7.0.dist-info/LICENSE-LGPL
crownstone_uart-2.7.0.dist-info/LICENSE-MIT
crownstone_uart-2.7.0.dist-info/METADATA
crownstone_uart-2.7.0.dist-info/WHEEL
crownstone_uart-2.7.0.dist-info/top_level.txt
crownstone_uart-2.7.0.dist-info/RECORD
