Metadata-Version: 2.1
Name: crownstone-uart
Version: 2.7.0
Summary: UNKNOWN
Home-page: https://github.com/crownstone/crownstone-lib-python-uart
Author: Crownstone B.V.
License: UNKNOWN
Platform: UNKNOWN
Classifier: Programming Language :: Python :: 3.7
Requires-Python: >=3.7
Requires-Dist: crownstone-core (~=3.2)
Requires-Dist: pyserial (~=3.4)
